llmdocgen/__init__.py
llmdocgen/enrich.py
llmdocgen/executor.py
llmdocgen/main.py
llmdocgen/settings.py
llmdocgen-0.1.2.dist-info/LICENSE
llmdocgen-0.1.2.dist-info/METADATA
llmdocgen-0.1.2.dist-info/WHEEL
llmdocgen-0.1.2.dist-info/top_level.txt
llmdocgen-0.1.2.dist-info/RECORD
