Metadata-Version: 2.1
Name: llmdocgen
Version: 0.1.2
Summary: Automate documentation generation using the LLM of your choice!
Home-page: https://github.com/gdoermann/llmdocgen
Author: Greg Doermann
Author-email: gdoermann+llmdocgen@gmail.com
License: MIT
Classifier: Development Status :: 4 - Beta
Classifier: Intended Audience :: Developers
Classifier: Operating System :: OS Independent
Classifier: Programming Language :: Python :: 3.9
Classifier: Programming Language :: Python :: 3.10
Classifier: Programming Language :: Python :: 3.11
Classifier: Programming Language :: Python :: 3.12
Classifier: Topic :: Software Development :: Libraries :: Python Modules
Classifier: Topic :: Utilities
Requires-Python: >=3.9
License-File: LICENSE
Requires-Dist: backoff
Requires-Dist: attrdict3
Requires-Dist: litellm
Requires-Dist: environs
Provides-Extra: extras
Requires-Dist: flake8 ; extra == 'extras'
Requires-Dist: twine ; extra == 'extras'
Requires-Dist: pytest ; extra == 'extras'
Requires-Dist: pip-tools ; extra == 'extras'
Requires-Dist: bumpver ; extra == 'extras'
Requires-Dist: coverage ; extra == 'extras'
